{".class": "MypyFile", "_fullname": "lab1", "is_partial_stub_package": false, "is_stub": false, "names": {".class": "SymbolTable", "App": {".class": "SymbolTableNode", "kind": "Gdef", "node": {".class": "TypeInfo", "_promote": null, "abstract_attributes": [], "bases": ["design.Ui_MainWindow"], "declared_metaclass": null, "defn": {".class": "ClassDef", "fullname": "lab1.App", "name": "App", "type_vars": []}, "flags": ["fallback_to_any"], "fullname": "lab1.App", "metaclass_type": null, "metadata": {}, "module_name": "lab1", "mro": ["lab1.App", "design.Ui_MainWindow", "builtins.object"], "names": {".class": "SymbolTable", "__init__": {".class": "SymbolTableNode", "kind": "Mdef", "node": {".class": "FuncDef", "arg_kinds": [0], "arg_names": ["self"], "flags": [], "fullname": "lab1.App.__init__", "name": "__init__", "type": null}}, "on_click": {".class": "SymbolTableNode", "kind": "Mdef", "node": {".class": "Decorator", "func": {".class": "FuncDef", "arg_kinds": [0], "arg_names": ["self"], "flags": ["is_decorated"], "fullname": "lab1.App.on_click", "name": "on_click", "type": null}, "is_overload": false, "var": {".class": "Var", "flags": ["is_initialized_in_class", "is_ready"], "fullname": null, "name": "on_click", "type": {".class": "AnyType", "missing_import_name": "lab1.pyqtSlot", "source_any": {".class": "AnyType", "missing_import_name": "lab1.pyqtSlot", "source_any": null, "type_of_any": 3}, "type_of_any": 7}}}}, "rotateAngle": {".class": "SymbolTableNode", "kind": "Mdef", "node": {".class": "FuncDef", "arg_kinds": [0], "arg_names": ["self"], "flags": [], "fullname": "lab1.App.rotateAngle", "name": "rotateAngle", "type": null}}}, "tuple_type": null, "type_vars": [], "typeddict_type": null}}, "CubeOpegl": {".class": "SymbolTableNode", "cross_ref": "CubeOpegl", "kind": "Gdef"}, "GL": {".class": "SymbolTableNode", "kind": "Gdef", "node": {".class": "Var", "flags": ["is_suppressed_import", "is_ready"], "fullname": "lab1.GL", "name": "GL", "type": {".class": "AnyType", "missing_import_name": "lab1.GL", "source_any": null, "type_of_any": 3}}}, "GLU": {".class": "SymbolTableNode", "kind": "Gdef", "node": {".class": "Var", "flags": ["is_suppressed_import", "is_ready"], "fullname": "lab1.GLU", "name": "GLU", "type": {".class": "AnyType", "missing_import_name": "lab1.GLU", "source_any": null, "type_of_any": 3}}}, "QApplication": {".class": "SymbolTableNode", "kind": "Gdef", "node": {".class": "Var", "flags": ["is_suppressed_import", "is_ready"], "fullname": "lab1.QApplication", "name": "QApplication", "type": {".class": "AnyType", "missing_import_name": "lab1.QApplication", "source_any": null, "type_of_any": 3}}}, "QIcon": {".class": "SymbolTableNode", "kind": "Gdef", "node": {".class": "Var", "flags": ["is_suppressed_import", "is_ready"], "fullname": "lab1.QIcon", "name": "QIcon", "type": {".class": "AnyType", "missing_import_name": "lab1.QIcon", "source_any": null, "type_of_any": 3}}}, "QMainWindow": {".class": "SymbolTableNode", "kind": "Gdef", "node": {".class": "Var", "flags": ["is_suppressed_import", "is_ready"], "fullname": "lab1.QMainWindow", "name": "QMainWindow", "type": {".class": "AnyType", "missing_import_name": "lab1.QMainWindow", "source_any": null, "type_of_any": 3}}}, "QMessageBox": {".class": "SymbolTableNode", "kind": "Gdef", "node": {".class": "Var", "flags": ["is_suppressed_import", "is_ready"], "fullname": "lab1.QMessageBox", "name": "QMessageBox", "type": {".class": "AnyType", "missing_import_name": "lab1.QMessageBox", "source_any": null, "type_of_any": 3}}}, "QPushButton": {".class": "SymbolTableNode", "kind": "Gdef", "node": {".class": "Var", "flags": ["is_suppressed_import", "is_ready"], "fullname": "lab1.QPushButton", "name": "QPushButton", "type": {".class": "AnyType", "missing_import_name": "lab1.QPushButton", "source_any": null, "type_of_any": 3}}}, "__doc__": {".class": "SymbolTableNode", "kind": "Gdef", "node": {".class": "Var", "flags": ["is_ready"], "fullname": "lab1.__doc__", "name": "__doc__", "type": "builtins.str"}}, "__file__": {".class": "SymbolTableNode", "kind": "Gdef", "node": {".class": "Var", "flags": ["is_ready"], "fullname": "lab1.__file__", "name": "__file__", "type": "builtins.str"}}, "__name__": {".class": "SymbolTableNode", "kind": "Gdef", "node": {".class": "Var", "flags": ["is_ready"], "fullname": "lab1.__name__", "name": "__name__", "type": "builtins.str"}}, "__package__": {".class": "SymbolTableNode", "kind": "Gdef", "node": {".class": "Var", "flags": ["is_ready"], "fullname": "lab1.__package__", "name": "__package__", "type": "builtins.str"}}, "app": {".class": "SymbolTableNode", "kind": "Gdef", "node": {".class": "Var", "flags": [], "fullname": "lab1.app", "name": "app", "type": {".class": "AnyType", "missing_import_name": "lab1.QApplication", "source_any": {".class": "AnyType", "missing_import_name": "lab1.QApplication", "source_any": null, "type_of_any": 3}, "type_of_any": 7}}}, "design": {".class": "SymbolTableNode", "cross_ref": "design", "kind": "Gdef"}, "ex": {".class": "SymbolTableNode", "kind": "Gdef", "node": {".class": "Var", "flags": [], "fullname": "lab1.ex", "name": "ex", "type": "lab1.App"}}, "math": {".class": "SymbolTableNode", "cross_ref": "math", "kind": "Gdef"}, "matmul": {".class": "SymbolTableNode", "kind": "Gdef", "node": {".class": "Var", "flags": ["is_suppressed_import", "is_ready"], "fullname": "lab1.matmul", "name": "matmul", "type": {".class": "AnyType", "missing_import_name": "lab1.matmul", "source_any": null, "type_of_any": 3}}}, "pyqtSlot": {".class": "SymbolTableNode", "kind": "Gdef", "node": {".class": "Var", "flags": ["is_suppressed_import", "is_ready"], "fullname": "lab1.pyqtSlot", "name": "pyqtSlot", "type": {".class": "AnyType", "missing_import_name": "lab1.pyqtSlot", "source_any": null, "type_of_any": 3}}}, "sys": {".class": "SymbolTableNode", "cross_ref": "sys", "kind": "Gdef"}}, "path": "/Users/irinalitvinova/MEGA/6 \u0441\u0435\u043c\u0435\u0441\u0442\u0440/\u041a\u043e\u043c\u043f\u044c\u044e\u0442\u0435\u0440\u043d\u0430\u044f \u0433\u0440\u0430\u0444\u0438\u043a\u0430/\u041b\u0430\u0431\u043e\u0440\u0430\u0442\u043e\u0440\u043d\u044b\u0435/\u041b\u0430\u0431\u043e\u0440\u0430\u0442\u043e\u0440\u043d\u0430\u044f 1/lab1.py"}